MANIFEST.in
requirements.txt
setup.py
unshred/__init__.py
unshred/my_threshold.py
unshred/sheet.py
unshred/split.py
unshred/threshold.py
unshred.egg-info/PKG-INFO
unshred.egg-info/SOURCES.txt
unshred.egg-info/dependency_links.txt
unshred.egg-info/requires.txt
unshred.egg-info/top_level.txt
unshred/features/__init__.py
unshred/features/base.py
unshred/features/colours.py
unshred/features/geometry.py
unshred/features/lines.py
unshred/static/base.css
unshred/static/checkerboard.png
unshred/static/jquery.magnific-popup.min.js
unshred/static/jquery.min.js
unshred/static/jquery.rwdImageMaps.min.js
unshred/templates/base.html
unshred/templates/index_sheet.html
unshred/templates/page.html