Metadata-Version: 1.0
Name: unshred
Version: 0.1.0
Summary: Set of tools to analyze scanned shreds and tag them
Home-page: https://github.com/dchaplinsky/unshred
Author: Dmitry Chaplinsky
Author-email: chaplinsky.dmitry@gmail.com
License: MIT
Platform: any
